netenum/__init__.py
netenum/__main__.py
netenum/core.py
netenum-0.1.1.dist-info/METADATA
netenum-0.1.1.dist-info/WHEEL
netenum-0.1.1.dist-info/RECORD
