Metadata-Version: 2.4
Name: netenum
Version: 0.1.1
Summary: Efficient IP address enumerator that interpolates across IPv4 and IPv6 CIDR ranges
Project-URL: Homepage, https://github.com/paigeadelethompson/python-netenum
Project-URL: Repository, https://github.com/paigeadelethompson/python-netenum.git
Author-email: Paige Thompson <paige@paige.bio>
License-Expression: MIT
Classifier: Development Status :: 3 - Alpha
Classifier: Intended Audience :: Developers
Classifier: License :: OSI Approved :: MIT License
Classifier: Programming Language :: Python :: 3
Classifier: Programming Language :: Python :: 3.8
Classifier: Programming Language :: Python :: 3.9
Classifier: Programming Language :: Python :: 3.10
Classifier: Programming Language :: Python :: 3.11
Classifier: Programming Language :: Python :: 3.12
Classifier: Programming Language :: Python :: 3.13
Classifier: Topic :: Internet
Classifier: Topic :: System :: Networking
Requires-Python: >=3.8
Provides-Extra: dev
Requires-Dist: black>=23.0; extra == 'dev'
Requires-Dist: flake8-bugbear>=24.0.0; extra == 'dev'
Requires-Dist: flake8-docstrings>=1.7.0; extra == 'dev'
Requires-Dist: flake8>=7.0.0; extra == 'dev'
Requires-Dist: isort>=5.0; extra == 'dev'
Requires-Dist: mypy>=1.0; extra == 'dev'
Requires-Dist: pylint>=3.0.0; extra == 'dev'
Requires-Dist: pytest-asyncio>=0.21.0; extra == 'dev'
Requires-Dist: pytest>=7.0; extra == 'dev'
